Workbook

Sheet Instructions
A1: CROWN PAINTS KENYA PLC - VALUATION MODEL
A4: Company Overview: | B4: Crown Paints Kenya PLC is the leading paint and coating manufacturer in East Africa
A5: Ticker: | B5: NSE: CRWN
A6: Sector: | B6: Building & Construction Materials
A8: Purpose: | B8: This model performs fundamental valuation analysis using DCF and multiples methods
A10: How to Use:
A11: 1. Company Information | B11: Review company data and current metrics in Assumptions sheet
A12: 2. Financial Data | B12: Historical FY2024 financial statements are pre-populated
A13: 3. Assumptions | B13: Adjust growth rates, discount rates, and terminal assumptions (yellow cells)
A14: 4. DCF Valuation | B14: Model calculates intrinsic value using discounted cash flow
A15: 5. Multiples Valuation | B15: Peer comparison using P/E, EV/EBITDA, and P/S multiples
A16: 6. Recommendation | B16: Review investment recommendation based on all valuation methods
A18: Color Coding:
A19: Blue Text | B19: User inputs - modify these values for scenario analysis
A20: Black Text | B20: Formulas and calculations
A21: Green Text | B21: Links to other sheets within the workbook
A22: Yellow Highlight | B22: Key assumptions requiring attention
A24: Data Sources: | B24: FY2024 Annual Report, NSE market data (as of Dec 2025)

Sheet Assumptions
A1: CROWN PAINTS KENYA PLC - VALUATION ASSUMPTIONS
A3: COMPANY INFORMATION
A4: Company Name | B4: Crown Paints Kenya PLC
A5: Ticker Symbol | B5: NSE: CRWN
A6: Sector | B6: Building Materials - Paints & Coatings
A7: Current Stock Price (KES) | B7: 60 | C7: Source: NSE as of Feb 13, 2025
A8: Shares Outstanding (millions) | B8: 142.36 | C8: Source: Company filings
A10: DCF MODEL ASSUMPTIONS
A11: Projection Period (years) | B11: 5
A12: Revenue Growth Rate - Year 1 (%) | B12: 0.1 | C12: Conservative vs FY24 19% volume growth
A13: Revenue Growth Rate - Year 2 (%) | B13: 0.09
A14: Revenue Growth Rate - Year 3 (%) | B14: 0.08
A15: Revenue Growth Rate - Year 4 (%) | B15: 0.07
A16: Revenue Growth Rate - Year 5 (%) | B16: 0.06
A18: EBITDA Margin % | B18: 0.11 | C18: Estimated based on operating margin ~6.8%
A19: Tax Rate % | B19: 0.3 | C19: Kenya corporate tax rate
A20: Capex as % of Revenue | B20: 0.02 | C20: Based on historical capex KES 292M
A21: D&A as % of Revenue | B21: 0.025
A22: Change in NWC as % of Revenue | B22: 0.015
A24: WACC / Discount Rate % | B24: 0.14 | C24: Emerging market premium included
A25: Terminal Growth Rate % | B25: 0.04 | C25: Long-term Kenya GDP growth estimate
A27: WACC COMPONENTS
A28: Risk-Free Rate (Kenya T-Bill) | B28: 0.12
A29: Market Risk Premium | B29: 0.08
A30: Beta | B30: 0.21 | C30: Low beta - defensive stock
A31: Cost of Equity (Calculated) | B31: =B28+B30*B29 -> 0.1368
A32: Cost of Debt (Pre-tax) | B32: 0.11
A33: Debt/Equity Ratio | B33: 0.12 | C33: Low leverage company
A35: PEER MULTIPLES BENCHMARKS
A36: Target P/E Multiple | B36: 9 | C36: Current: 8.1x, industry avg ~9-10x
A37: Target EV/EBITDA Multiple | B37: 5.5 | C37: Current: 4.69x, conservative target
A38: Target P/S Multiple | B38: 0.6

Sheet Financial Data
A1: CROWN PAINTS KENYA - FY2024 FINANCIAL DATA
A3: Base Year: FY2024 (Year ended December 31, 2024)
A5: INCOME STATEMENT (KES Millions)
A6: Revenue | B6: 13500 | C6: Source: FY2024 Annual Report
A7: Gross Profit | B7: 5994 | C7: Gross margin: 44.4%
A8: Operating Profit (EBIT) | B8: 787 | C8: Operating margin: 5.8%
A9: EBITDA (Estimated) | B9: =B8+B11 -> 1124.5
A10: Profit Before Tax | B10: 787
A11: Depreciation & Amortization (Est.) | B11: =B6*Assumptions!$B$21 -> 337.5
A12: Tax Expense | B12: 243 | C12: Effective tax rate ~31%
A13: Net Income | B13: 544 | C13: Net margin: 4.0%
A14: EPS (KES) | B14: 3.82
A16: BALANCE SHEET (KES Millions)
A17: Cash & Equivalents | B17: 635
A18: Total Debt | B18: 440
A19: Net Debt (Cash) | B19: =B18-B17 -> -195 | C19: Net cash position
A20: Total Equity | B20: 3400
A22: CASH FLOW (KES Millions)
A23: Operating Cash Flow | B23: 1810
A24: Capital Expenditures | B24: 292
A25: Free Cash Flow | B25: =B23-B24 -> 1518
K26: .
A27: CURRENT VALUATION METRICS
A28: Market Cap (KES millions) | B28: =Assumptions!$B$7*Assumptions!$B$8 -> 8541.6
A29: Enterprise Value (KES millions) | B29: =B28+B19 -> 8346.6
A30: Current P/E Ratio | B30: =B28/B13 -> 15.701471
A31: Current EV/EBITDA | B31: =B29/B9 -> 7.4224989
A32: Current P/S Ratio | B32: =B28/B6 -> 0.63271111
A33: Dividend per Share (KES) | B33: 3
A34: Current Share Price | B34: 60
A35: Dividend Yield | B35: =B33/B34 -> 0.05

Sheet DCF Valuation
A1: CROWN PAINTS KENYA - DCF VALUATION
A2: All amounts in KES Millions except per share values
A4: Projection Period | B4: Year 1 | C4: Year 2 | D4: Year 3 | E4: Year 4 | F4: Year 5
A5: Revenue | B5: ='Financial Data'!$B$6*(1+Assumptions!$B$12) -> 14850 | C5: =B5*(1+Assumptions!$B$13) -> 16186.5 | D5: =C5*(1+Assumptions!$B$14) -> 17481.42 | E5: =D5*(1+Assumptions!$B$15) -> 18705.119 | F5: =E5*(1+Assumptions!$B$16) -> 19827.427
A6: EBITDA | B6: =B5*Assumptions!$B$18 -> 1633.5 | C6: =C5*Assumptions!$B$18 -> 1780.515 | D6: =D5*Assumptions!$B$18 -> 1922.9562 | E6: =E5*Assumptions!$B$18 -> 2057.5631 | F6: =F5*Assumptions!$B$18 -> 2181.0169
A7: Less: D&A | B7: =B5*Assumptions!$B$21 -> 371.25 | C7: =C5*Assumptions!$B$21 -> 404.6625 | D7: =D5*Assumptions!$B$21 -> 437.0355 | E7: =E5*Assumptions!$B$21 -> 467.62799 | F7: =F5*Assumptions!$B$21 -> 495.68566
A8: EBIT | B8: =B6-B7 -> 1262.25 | C8: =C6-C7 -> 1375.8525 | D8: =D6-D7 -> 1485.9207 | E8: =E6-E7 -> 1589.9351 | F8: =F6-F7 -> 1685.3313
A9: Less: Tax | B9: =B8*Assumptions!$B$19 -> 378.675 | C9: =C8*Assumptions!$B$19 -> 412.75575 | D9: =D8*Assumptions!$B$19 -> 445.77621 | E9: =E8*Assumptions!$B$19 -> 476.98054 | F9: =F8*Assumptions!$B$19 -> 505.59938
A10: NOPAT | B10: =B8-B9 -> 883.575 | C10: =C8-C9 -> 963.09675 | D10: =D8-D9 -> 1040.1445 | E10: =E8-E9 -> 1112.9546 | F10: =F8-F9 -> 1179.7319
A11: Add: D&A | B11: =B7 -> 371.25 | C11: =C7 -> 404.6625 | D11: =D7 -> 437.0355 | E11: =E7 -> 467.62799 | F11: =F7 -> 495.68566
A12: Less: Capex | B12: =B5*Assumptions!$B$20 -> 297 | C12: =C5*Assumptions!$B$20 -> 323.73 | D12: =D5*Assumptions!$B$20 -> 349.6284 | E12: =E5*Assumptions!$B$20 -> 374.10239 | F12: =F5*Assumptions!$B$20 -> 396.54853
A13: Less: Δ NWC | B13: =B5*Assumptions!$B$22 -> 222.75 | C13: =C5*Assumptions!$B$22 -> 242.7975 | D13: =D5*Assumptions!$B$22 -> 262.2213 | E13: =E5*Assumptions!$B$22 -> 280.57679 | F13: =F5*Assumptions!$B$22 -> 297.4114
A14: Unlevered FCF | B14: =B10+B11-B12-B13 -> 735.075 | C14: =C10+C11-C12-C13 -> 801.23175 | D14: =D10+D11-D12-D13 -> 865.33029 | E14: =E10+E11-E12-E13 -> 925.90341 | F14: =F10+F11-F12-F13 -> 981.45761
A16: Discount Factor | B16: =1/((1+Assumptions!$B$24)^1) -> 0.87719298 | C16: =1/((1+Assumptions!$B$24)^2) -> 0.76946753 | D16: =1/((1+Assumptions!$B$24)^3) -> 0.67497152 | E16: =1/((1+Assumptions!$B$24)^4) -> 0.59208028 | F16: =1/((1+Assumptions!$B$24)^5) -> 0.51936866
A17: PV of FCF | B17: =B14*B16 -> 644.80263 | C17: =C14*C16 -> 616.52181 | D17: =D14*D16 -> 584.0733 | E17: =E14*E16 -> 548.20915 | F17: =F14*F16 -> 509.73833
A19: TERMINAL VALUE CALCULATION
A20: Terminal Year FCF | B20: =F14*(1+Assumptions!$B$25) -> 1020.7159
A21: Terminal Value | B21: =B20/(Assumptions!$B$24-Assumptions!$B$25) -> 10207.159
A22: PV of Terminal Value | B22: =B21*F16 -> 5301.2786
A24: VALUATION SUMMARY
A25: Sum of PV of FCF | B25: =SUM(B17:F17) -> 2903.3452
A26: PV of Terminal Value | B26: =B22 -> 5301.2786
A27: Enterprise Value | B27: =B25+B26 -> 8204.6239
A28: Less: Net Debt (Add: Net Cash) | B28: ='Financial Data'!$B$19 -> -195
A29: Equity Value | B29: =B27-B28 -> 8399.6239
A30: Shares Outstanding (millions) | B30: =Assumptions!$B$8 -> 142.36
A31: DCF Fair Value per Share (KES) | B31: =B29/B30 -> 59.002696
A33: Current Stock Price (KES) | B33: =Assumptions!$B$7 -> 60
A34: Upside/(Downside) % | B34: =(B31-B33)/B33 -> -0.016621727

Sheet Multiples Valuation
A1: CROWN PAINTS KENYA - MULTIPLES VALUATION
A2: All amounts in KES Millions except per share values
A4: VALUATION BY COMPARABLE MULTIPLES
A6: P/E RATIO METHOD
A7: Net Income | B7: ='Financial Data'!$B$13 -> 544
A8: Target P/E Multiple | B8: =Assumptions!$B$36 -> 9
A9: Implied Market Cap | B9: =B7*B8 -> 4896
A10: Shares Outstanding (millions) | B10: =Assumptions!$B$8 -> 142.36
A11: P/E Fair Value per Share (KES) | B11: =B9/B10 -> 34.391683
A13: EV/EBITDA METHOD
A14: EBITDA | B14: ='Financial Data'!$B$9 -> 1124.5
A15: Target EV/EBITDA Multiple | B15: =Assumptions!$B$37 -> 5.5
A16: Implied Enterprise Value | B16: =B14*B15 -> 6184.75
A17: Less: Net Debt (Add: Net Cash) | B17: ='Financial Data'!$B$19 -> -195
A18: Implied Equity Value | B18: =B16-B17 -> 6379.75
A19: Shares Outstanding (millions) | B19: =Assumptions!$B$8 -> 142.36
A20: EV/EBITDA Fair Value per Share (KES) | B20: =B18/B19 -> 44.814203
A22: P/S (PRICE-TO-SALES) METHOD
A23: Revenue | B23: ='Financial Data'!$B$6 -> 13500
A24: Target P/S Multiple | B24: =Assumptions!$B$38 -> 0.6
A25: Implied Market Cap | B25: =B23*B24 -> 8100
A26: Shares Outstanding (millions) | B26: =Assumptions!$B$8 -> 142.36
A27: P/S Fair Value per Share (KES) | B27: =B25/B26 -> 56.898005

Sheet Summary & Recommendation
A1: CROWN PAINTS KENYA PLC - INVESTMENT RECOMMENDATION
A3: Company: | B3: =Assumptions!$B$4 -> Crown Paints Kenya PLC
A4: Ticker: | B4: =Assumptions!$B$5 -> NSE: CRWN
A5: Sector: | B5: =Assumptions!$B$6 -> Building Materials - Paints & Coatings
A6: Current Price (KES): | B6: =Assumptions!$B$7 -> 60
A7: Date: | B7: 46054
A9: VALUATION SUMMARY
A10: Valuation Method | B10: Fair Value (KES) | C10: Current Price | D10: Upside/(Downside)
A11: DCF Valuation | B11: ='DCF Valuation'!$B$31 -> 59.002696 | C11: =B6 -> 60 | D11: =(B11-C11)/C11 -> -0.016621727 | G11: =0.6*B11 -> 35.401618
A12: P/E Multiple | B12: ='Multiples Valuation'!$B$11 -> 34.391683 | C12: =B6 -> 60 | D12: =(B12-C12)/C12 -> -0.42680528 | G12: =0.2*B12 -> 6.8783366
A13: EV/EBITDA Multiple | B13: ='Multiples Valuation'!$B$20 -> 44.814203 | C13: =B6 -> 60 | D13: =(B13-C13)/C13 -> -0.25309661 | G13: =0.1*B13 -> 4.4814203
A14: P/S Multiple | B14: ='Multiples Valuation'!$B$27 -> 56.898005 | C14: =B6 -> 60 | D14: =(B14-C14)/C14 -> -0.051699916 | G14: =0.1*B14 -> 5.6898005
A16: Average Fair Value | B16: =AVERAGE(B11:B14) -> 48.776647 | D16: =AVERAGE(D11:D14) -> -0.18705588 | G16: =SUM(G11:G14) -> 52.451175
A18: KEY FINANCIAL METRICS (FY2024)
A19: Revenue (KES millions) | B19: ='Financial Data'!$B$6 -> 13500
A20: Net Income (KES millions) | B20: ='Financial Data'!$B$13 -> 544
A21: Market Cap (KES millions) | B21: ='Financial Data'!$B$28 -> 8541.6
A22: Enterprise Value (KES millions) | B22: ='Financial Data'!$B$29 -> 8346.6
A23: Current P/E Ratio | B23: ='Financial Data'!$B$30 -> 15.701471
A24: Current EV/EBITDA | B24: ='Financial Data'!$B$31 -> 7.4224989
A25: ROE | B25: 0.2669
A26: Dividend Yield | B26: ='Financial Data'!$B$35 -> 0.05
A28: INVESTMENT RECOMMENDATION
A30: Recommendation: | B30: =IF(D16>0.2,"STRONG BUY",IF(D16>0.1,"BUY",IF(D16>0,"HOLD",IF(D16>-0.1,"UNDERPERFORM","HOLD")))) -> HOLD
A32: Target Price (Avg): | B32: =B16 -> 48.776647
A33: Potential Return: | B33: =D16 -> -0.18705588
A35: INVESTMENT THESIS
A36: Strengths:
A37: • Market leader in East African paints & coatings
A38: • Strong recovery with 8% revenue growth in FY2024
A39: • Healthy cash generation (FCF: KES 1.5B)
A40: • Net cash position (KES 195M)
A41: • High ROE of 26.7%, attractive dividend yield
A42: • Low beta (0.21) - defensive characteristics
A44: Risks:
A45: • Currency volatility in regional markets
A46: • Competition from international players
A47: • Sensitivity to construction sector cyclicality
... A55: SELL: <-10%
